sonusai_torchl/__init__.py
sonusai_torchl/torchl2aoti.py
sonusai_torchl/torchl_onnx.py
sonusai_torchl/torchl_predict.py
sonusai_torchl/torchl_train.py
sonusai_torchl/data_generator/__init__.py
sonusai_torchl/data_generator/dataloader_utils.py
sonusai_torchl/data_generator/mixdb_dataset.py
sonusai_torchl/data_generator/speaker_id_mixdb_dataset.py
sonusai_torchl/data_generator/streaming_mixdb_dataset.py
sonusai_torchl/utils/__init__.py
sonusai_torchl/utils/torchl_utils.py
sonusai_torchl-1.1.1.dist-info/METADATA
sonusai_torchl-1.1.1.dist-info/WHEEL
sonusai_torchl-1.1.1.dist-info/RECORD
